funasr/__init__.py
funasr/register.py
funasr/version.txt
funasr/auto/__init__.py
funasr/auto/auto_frontend.py
funasr/auto/auto_model.py
funasr/auto/auto_tokenizer.py
funasr/bin/__init__.py
funasr/bin/compute_audio_cmvn.py
funasr/bin/export.py
funasr/bin/inference.py
funasr/bin/tokenize_text.py
funasr/bin/train.py
funasr/bin/train_ds.py
funasr/datasets/__init__.py
funasr/datasets/dataloader_entry.py
funasr/datasets/audio_datasets/__init__.py
funasr/datasets/audio_datasets/datasets.py
funasr/datasets/audio_datasets/espnet_samplers.py
funasr/datasets/audio_datasets/index_ds.py
funasr/datasets/audio_datasets/jsonl2scp.py
funasr/datasets/audio_datasets/preprocessor.py
funasr/datasets/audio_datasets/samplers.py
funasr/datasets/audio_datasets/scp2jsonl.py
funasr/datasets/audio_datasets/scp2len.py
funasr/datasets/audio_datasets/sensevoice2jsonl.py
funasr/datasets/audio_datasets/update_jsonl.py
funasr/datasets/fun_asr_datasets/__init__.py
funasr/datasets/fun_asr_datasets/datasets.py
funasr/datasets/fun_asr_datasets/multicontext_prompt.py
funasr/datasets/kws_datasets/__init__.py
funasr/datasets/kws_datasets/datasets.py
funasr/datasets/llm_datasets/__init__.py
funasr/datasets/llm_datasets/datasets.py
funasr/datasets/llm_datasets/preprocessor.py
funasr/datasets/llm_datasets_qwenaudio/__init__.py
funasr/datasets/llm_datasets_qwenaudio/datasets.py
funasr/datasets/llm_datasets_vicuna/__init__.py
funasr/datasets/llm_datasets_vicuna/datasets.py
funasr/datasets/openai_datasets/__init__.py
funasr/datasets/openai_datasets/datasets.py
funasr/datasets/openai_datasets/index_ds.py
funasr/datasets/sense_voice_datasets/__init__.py
funasr/datasets/sense_voice_datasets/datasets.py
funasr/download/__init__.py
funasr/download/download_dataset_from_hub.py
funasr/download/download_model_from_hub.py
funasr/download/file.py
funasr/download/name_maps_from_hub.py
funasr/download/runtime_sdk_download_tool.py
funasr/frontends/__init__.py
funasr/frontends/default.py
funasr/frontends/eend_ola_feature.py
funasr-1.3.1.dist-info/LICENSE
funasr-1.3.1.dist-info/METADATA
funasr-1.3.1.dist-info/WHEEL
funasr-1.3.1.dist-info/entry_points.txt
funasr-1.3.1.dist-info/top_level.txt
funasr-1.3.1.dist-info/RECORD
