Metadata-Version: 2.1
Name: funasr
Version: 1.3.1
Summary: FunASR: A Fundamental End-to-End Speech Recognition Toolkit
Home-page: https://github.com/alibaba-damo-academy/FunASR.git
Author: Speech Lab of Alibaba Group
Author-email: funasr@list.alibaba-inc.com
License: The MIT License
Classifier: Programming Language :: Python
Classifier: Programming Language :: Python :: 3
Classifier: Programming Language :: Python :: 3.7
Classifier: Programming Language :: Python :: 3.8
Classifier: Programming Language :: Python :: 3.9
Classifier: Development Status :: 5 - Production/Stable
Classifier: Intended Audience :: Science/Research
Classifier: Operating System :: POSIX :: Linux
Classifier: License :: OSI Approved :: Apache Software License
Classifier: Topic :: Software Development :: Libraries :: Python Modules
Requires-Python: >=3.7.0
License-File: LICENSE
Requires-Dist: scipy>=1.4.1
Requires-Dist: librosa
Requires-Dist: jamo
Requires-Dist: PyYAML>=5.1.2
Requires-Dist: soundfile>=0.12.1
Requires-Dist: kaldiio>=2.17.0
Requires-Dist: torch-complex
Requires-Dist: sentencepiece
Requires-Dist: jieba
Requires-Dist: pytorch-wpe
Requires-Dist: editdistance>=0.5.2
Requires-Dist: oss2
Requires-Dist: tqdm
Requires-Dist: umap-learn
Requires-Dist: jaconv
Requires-Dist: hydra-core>=1.3.2
Requires-Dist: tensorboardX
Requires-Dist: requests
Requires-Dist: modelscope
Provides-Extra: all
Requires-Dist: torch-optimizer; extra == "all"
Requires-Dist: fairscale; extra == "all"
Requires-Dist: transformers; extra == "all"
Requires-Dist: openai-whisper; extra == "all"
Requires-Dist: editdistance; extra == "all"
Requires-Dist: transformers>=4.32.0; extra == "all"
Requires-Dist: accelerate; extra == "all"
Requires-Dist: tiktoken; extra == "all"
Requires-Dist: einops; extra == "all"
Requires-Dist: transformers-stream-generator>=0.0.4; extra == "all"
Requires-Dist: scipy; extra == "all"
Requires-Dist: torchvision; extra == "all"
Requires-Dist: pillow; extra == "all"
Requires-Dist: matplotlib; extra == "all"
Provides-Extra: doc
Requires-Dist: Jinja2; extra == "doc"
Requires-Dist: Sphinx; extra == "doc"
Requires-Dist: sphinx-rtd-theme>=0.2.4; extra == "doc"
Requires-Dist: sphinx-argparse>=0.2.5; extra == "doc"
Requires-Dist: commonmark; extra == "doc"
Requires-Dist: recommonmark>=0.4.0; extra == "doc"
Requires-Dist: nbsphinx>=0.4.2; extra == "doc"
Requires-Dist: sphinx-markdown-tables>=0.0.12; extra == "doc"
Requires-Dist: configargparse>=1.2.1; extra == "doc"
Provides-Extra: llm
Requires-Dist: transformers>=4.32.0; extra == "llm"
Requires-Dist: accelerate; extra == "llm"
Requires-Dist: tiktoken; extra == "llm"
Requires-Dist: einops; extra == "llm"
Requires-Dist: transformers-stream-generator>=0.0.4; extra == "llm"
Requires-Dist: scipy; extra == "llm"
Requires-Dist: torchvision; extra == "llm"
Requires-Dist: pillow; extra == "llm"
Requires-Dist: matplotlib; extra == "llm"
Provides-Extra: test
Requires-Dist: pytest>=3.3.0; extra == "test"
Requires-Dist: pytest-timeouts>=1.2.1; extra == "test"
Requires-Dist: pytest-pythonpath>=0.7.3; extra == "test"
Requires-Dist: pytest-cov>=2.7.1; extra == "test"
Requires-Dist: hacking>=2.0.0; extra == "test"
Requires-Dist: mock>=2.0.0; extra == "test"
Requires-Dist: pycodestyle; extra == "test"
Requires-Dist: jsondiff<2.0.0,>=1.2.0; extra == "test"
Requires-Dist: flake8>=3.7.8; extra == "test"
Requires-Dist: flake8-docstrings>=1.3.1; extra == "test"
Requires-Dist: black; extra == "test"
Requires-Dist: editdistance; extra == "test"
Provides-Extra: train
Requires-Dist: editdistance; extra == "train"
